DingTouGaibianmingyunFix1/README.md
DingTouGaibianmingyunFix1/__init__.py
DingTouGaibianmingyunFix1/__main__.py
DingTouGaibianmingyunFix1/file.epub
DingTouGaibianmingyunFix1/index.html
DingTouGaibianmingyunFix1/css/__init__.py
DingTouGaibianmingyunFix1/css/annotations.css
DingTouGaibianmingyunFix1/css/main.css
DingTouGaibianmingyunFix1/css/normalize.css
DingTouGaibianmingyunFix1/css/popup.css
DingTouGaibianmingyunFix1/font/__init__.py
DingTouGaibianmingyunFix1/font/fontello.eot
DingTouGaibianmingyunFix1/font/fontello.svg
DingTouGaibianmingyunFix1/font/fontello.ttf
DingTouGaibianmingyunFix1/font/fontello.woff
DingTouGaibianmingyunFix1/img/__init__.py
DingTouGaibianmingyunFix1/img/annotator-glyph-sprite.png
DingTouGaibianmingyunFix1/img/annotator-icon-sprite.png
DingTouGaibianmingyunFix1/img/apple-touch-icon.png
DingTouGaibianmingyunFix1/img/cancelfullscreen.png
DingTouGaibianmingyunFix1/img/close.png
DingTouGaibianmingyunFix1/img/fullscreen.png
DingTouGaibianmingyunFix1/img/loader.gif
DingTouGaibianmingyunFix1/img/menu-icon.png
DingTouGaibianmingyunFix1/img/save.png
DingTouGaibianmingyunFix1/img/saved.png
DingTouGaibianmingyunFix1/img/settings-s.png
DingTouGaibianmingyunFix1/img/settings.png
DingTouGaibianmingyunFix1/img/star.png
DingTouGaibianmingyunFix1/js/__init__.py
DingTouGaibianmingyunFix1/js/epub.js
DingTouGaibianmingyunFix1/js/epub.min.js
DingTouGaibianmingyunFix1/js/epub.min.map
DingTouGaibianmingyunFix1/js/hooks.min.js
DingTouGaibianmingyunFix1/js/hooks.min.map
DingTouGaibianmingyunFix1/js/reader.js
DingTouGaibianmingyunFix1/js/reader.js.map
DingTouGaibianmingyunFix1/js/reader.min.js
DingTouGaibianmingyunFix1/js/reader.min.map
DingTouGaibianmingyunFix1/js/hooks/__init__.py
DingTouGaibianmingyunFix1/js/hooks/extensions/__init__.py
DingTouGaibianmingyunFix1/js/hooks/extensions/highlight.js
DingTouGaibianmingyunFix1/js/libs/__init__.py
DingTouGaibianmingyunFix1/js/libs/jquery.min.js
DingTouGaibianmingyunFix1/js/libs/localforage.min.js
ding_tou_gaibianmingyun_fix1-2025.3.24.2.dist-info/METADATA
ding_tou_gaibianmingyun_fix1-2025.3.24.2.dist-info/WHEEL
ding_tou_gaibianmingyun_fix1-2025.3.24.2.dist-info/entry_points.txt
ding_tou_gaibianmingyun_fix1-2025.3.24.2.dist-info/top_level.txt
ding_tou_gaibianmingyun_fix1-2025.3.24.2.dist-info/RECORD
